{
  "label": "Center",
  "icon": "group",
  "seq": 600,
  "submenu": [
    {
      "label": "Sharing Sheet",
      "state": "app.sharingsheet",
      "p": "SHARINGSHEET_WRITE",
      "seq": 100
    },
    {
      "label": "Holidays",
      "state": "app.holiday",
      "p": "HOLIDAY_WRITE",
      "seq": 200
    },
    {
      "label": "Food Menu",
      "state": "app.foodmenu",
      "p": "CENTER_WRITE",
      "seq": 300
    },
    {
      "label": "Hygiene",
      "state": "app.hygiene",
      "p": "HYGIENE_WRITE",
      "seq": 400
    },
    {
      "label": "Group Activity",
      "state": "app.activity",
      "p": "GROUP_ACTIVITY_WRITE",
      "seq": 500
    },
    {
      "label": "Gallery",
      "state": "app.gallery",
      "p": "GALLERY_WRITE",
      "seq": 600
    }
  ]
}